causal_priority_queue/__init__.py
causal_priority_queue/cpq.py
causal_priority_queue-1.0.0.dist-info/LICENSE
causal_priority_queue-1.0.0.dist-info/METADATA
causal_priority_queue-1.0.0.dist-info/WHEEL
causal_priority_queue-1.0.0.dist-info/top_level.txt
causal_priority_queue-1.0.0.dist-info/RECORD
