Metadata-Version: 2.2
Name: causal-priority-queue
Version: 1.0.0
Summary: A dynamically adjusting priority queue with causal influences.
Home-page: https://github.com/mukerjeejoy-github/causal-priority-queue
Author: Joy Mukerjee
Author-email: mukerjeejoy@protonmail.com
Classifier: Programming Language :: Python :: 3
Classifier: License :: OSI Approved :: MIT License
Classifier: Operating System :: OS Independent
Requires-Python: >=3.6
License-File: LICENSE
Dynamic: author
Dynamic: author-email
Dynamic: classifier
Dynamic: description
Dynamic: description-content-type
Dynamic: home-page
Dynamic: requires-python
Dynamic: summary
